[
  {
    "name": "__cf_bm",
    "value": "A84UsKk00Zbgas_6.KYtTNRJAjvj8nzZAu0Qa.mz5dA-1770477259.4111571-1.0.1.1-iCXRl8LTZYqTwewFQb5M8uzq_yAqHkx8aXOKgFgRpwoWlJYte89WJnNHx7bvRO39jt4hc7f.LxPSyOEHq4Vc0X3GxA4IWOy43JpsFO3xO07rdXkGFTh.qSWkCsN77.77",
    "domain": ".x.com",
    "path": "/",
    "expires": 1770479060.804986,
    "size": 206,
    "httpOnly": true,
    "secure": true,
    "session": false,
    "priority": "Medium",
    "sameParty": false,
    "sourceScheme": "Secure"
  },
  {
    "name": "twid",
    "value": "u%3D2020152869660553216",
    "domain": ".x.com",
    "path": "/",
    "expires": 1802013250.585935,
    "size": 27,
    "httpOnly": false,
    "secure": true,
    "session": false,
    "sameSite": "None",
    "priority": "Medium",
    "sameParty": false,
    "sourceScheme": "Secure"
  },
  {
    "name": "lang",
    "value": "en",
    "domain": "x.com",
    "path": "/",
    "expires": -1,
    "size": 6,
    "httpOnly": false,
    "secure": false,
    "session": true,
    "priority": "Medium",
    "sameParty": false,
    "sourceScheme": "Secure"
  },
  {
    "name": "gt",
    "value": "2020153852717130031",
    "domain": ".x.com",
    "path": "/",
    "expires": 1770486188.619099,
    "size": 21,
    "httpOnly": false,
    "secure": true,
    "session": false,
    "priority": "Medium",
    "sameParty": false,
    "sourceScheme": "Secure"
  },
  {
    "name": "ct0",
    "value": "1cccc47919f0514ec74afc6ced1042322b3e6ef241c58adf7443c76d67e46eb448991f22d36d37d363d4b27b1b3117c02e16fe49c128535e2d6ac87254c7e0915998012d07481f783bb2590d06f77795",
    "domain": ".x.com",
    "path": "/",
    "expires": 1805037245.331531,
    "size": 163,
    "httpOnly": false,
    "secure": true,
    "session": false,
    "sameSite": "Lax",
    "priority": "Medium",
    "sameParty": false,
    "sourceScheme": "Secure"
  },
  {
    "name": "__cuid",
    "value": "4f904209ac214630ab9e8938940a0c74",
    "domain": ".x.com",
    "path": "/",
    "expires": 1805037248,
    "size": 38,
    "httpOnly": false,
    "secure": false,
    "session": false,
    "sameSite": "Lax",
    "priority": "Medium",
    "sameParty": false,
    "sourceScheme": "Secure"
  },
  {
    "name": "att",
    "value": "1-R9XzegDLsqHz08ufAyBbR7bdbj1iUj0EOJI6l6qa",
    "domain": ".x.com",
    "path": "/",
    "expires": 1770563646.011581,
    "size": 45,
    "httpOnly": true,
    "secure": true,
    "session": false,
    "sameSite": "None",
    "priority": "Medium",
    "sameParty": false,
    "sourceScheme": "Secure"
  },
  {
    "name": "auth_token",
    "value": "7e1a4d993c2f20b5cfcdff9a47b65d0fdbb74f99",
    "domain": ".x.com",
    "path": "/",
    "expires": 1805037244.601722,
    "size": 50,
    "httpOnly": true,
    "secure": true,
    "session": false,
    "sameSite": "None",
    "priority": "Medium",
    "sameParty": false,
    "sourceScheme": "Secure"
  },
  {
    "name": "personalization_id",
    "value": "\"v1_XVdaY8XEejqyaBdkK9n+DA==\"",
    "domain": ".x.com",
    "path": "/",
    "expires": 1805037188.618936,
    "size": 47,
    "httpOnly": false,
    "secure": true,
    "session": false,
    "sameSite": "None",
    "priority": "Medium",
    "sameParty": false,
    "sourceScheme": "Secure"
  },
  {
    "name": "g_state",
    "value": "{\"i_l\":0,\"i_ll\":1770477202849,\"i_e\":{\"enable_itp_optimization\":0}}",
    "domain": "x.com",
    "path": "/",
    "expires": 1786029241,
    "size": 73,
    "httpOnly": false,
    "secure": false,
    "session": false,
    "priority": "Medium",
    "sameParty": false,
    "sourceScheme": "Secure"
  },
  {
    "name": "guest_id",
    "value": "v1%3A177047718575300341",
    "domain": ".x.com",
    "path": "/",
    "expires": 1805037188.390402,
    "size": 31,
    "httpOnly": false,
    "secure": true,
    "session": false,
    "sameSite": "None",
    "priority": "Medium",
    "sameParty": false,
    "sourceScheme": "Secure"
  },
  {
    "name": "guest_id_marketing",
    "value": "v1%3A177047718575300341",
    "domain": ".x.com",
    "path": "/",
    "expires": 1805037250.585611,
    "size": 41,
    "httpOnly": false,
    "secure": true,
    "session": false,
    "sameSite": "None",
    "priority": "Medium",
    "sameParty": false,
    "sourceScheme": "Secure"
  },
  {
    "name": "guest_id_ads",
    "value": "v1%3A177047718575300341",
    "domain": ".x.com",
    "path": "/",
    "expires": 1805037250.585327,
    "size": 35,
    "httpOnly": false,
    "secure": true,
    "session": false,
    "sameSite": "None",
    "priority": "Medium",
    "sameParty": false,
    "sourceScheme": "Secure"
  },
  {
    "name": "kdt",
    "value": "XONy7pnqIdjJfRKooelFO5MmKgGNiT4uWS1iFEWb",
    "domain": ".x.com",
    "path": "/",
    "expires": 1805037244.601307,
    "size": 43,
    "httpOnly": true,
    "secure": true,
    "session": false,
    "priority": "Medium",
    "sameParty": false,
    "sourceScheme": "Secure"
  }
]